boundlessgeo_schema
