Metadata-Version: 1.1
Name: boundlessgeo-schema
Version: 0.16.1
Summary: schema for boundlessgeo actions
Home-page: https://github.com/boundlessgeo/schema
Author: Boundless Spatial
Author-email: contact@boundlessgeo.com
License: Public Domain
Keywords: schema,json,dict
Platform: UNKNOWN
Classifier: Topic :: Utilities
Classifier: Intended Audience :: System Administrators
Classifier: Environment :: Web Environment
Classifier: License :: OSI Approved :: Apache Software License
Classifier: Development Status :: 3 - Alpha
Classifier: Operating System :: Other OS
